{
  "maincss.js": "js/maincss-3d5b3849a427f564a3ab.js",
  "maincss.css": "maincss-3d5b3849a427f564a3ab.css",
  "mainjs.js": "js/mainjs-3d5b3849a427f564a3ab.js",
  "fonts/fa-brands-400.eot": "fonts/fa-brands-400.eot",
  "fonts/fa-brands-400.svg": "fonts/fa-brands-400.svg",
  "fonts/fa-brands-400.ttf": "fonts/fa-brands-400.ttf",
  "fonts/fa-brands-400.woff": "fonts/fa-brands-400.woff",
  "fonts/fa-brands-400.woff2": "fonts/fa-brands-400.woff2",
  "fonts/fa-regular-400.eot": "fonts/fa-regular-400.eot",
  "fonts/fa-regular-400.svg": "fonts/fa-regular-400.svg",
  "fonts/fa-regular-400.ttf": "fonts/fa-regular-400.ttf",
  "fonts/fa-regular-400.woff": "fonts/fa-regular-400.woff",
  "fonts/fa-regular-400.woff2": "fonts/fa-regular-400.woff2",
  "fonts/fa-solid-900.eot": "fonts/fa-solid-900.eot",
  "fonts/fa-solid-900.svg": "fonts/fa-solid-900.svg",
  "fonts/fa-solid-900.ttf": "fonts/fa-solid-900.ttf",
  "fonts/fa-solid-900.woff": "fonts/fa-solid-900.woff",
  "fonts/fa-solid-900.woff2": "fonts/fa-solid-900.woff2",
  "images/.DS_Store": "images/.DS_Store",
  "images/favicon.ico": "images/favicon.ico",
  "images/gallery/fulls/01.jpg": "images/gallery/fulls/01.jpg",
  "images/gallery/fulls/02.jpg": "images/gallery/fulls/02.jpg",
  "images/gallery/fulls/03.jpg": "images/gallery/fulls/03.jpg",
  "images/gallery/fulls/04.jpg": "images/gallery/fulls/04.jpg",
  "images/gallery/fulls/05.jpg": "images/gallery/fulls/05.jpg",
  "images/gallery/fulls/06.jpg": "images/gallery/fulls/06.jpg",
  "images/gallery/fulls/07.jpg": "images/gallery/fulls/07.jpg",
  "images/gallery/fulls/08.jpg": "images/gallery/fulls/08.jpg",
  "images/gallery/fulls/09.jpg": "images/gallery/fulls/09.jpg",
  "images/gallery/fulls/10.jpg": "images/gallery/fulls/10.jpg",
  "images/gallery/thumbs/01.jpg": "images/gallery/thumbs/01.jpg",
  "images/gallery/thumbs/02.jpg": "images/gallery/thumbs/02.jpg",
  "images/gallery/thumbs/03.jpg": "images/gallery/thumbs/03.jpg",
  "images/gallery/thumbs/04.jpg": "images/gallery/thumbs/04.jpg",
  "images/gallery/thumbs/05.jpg": "images/gallery/thumbs/05.jpg",
  "images/gallery/thumbs/06.jpg": "images/gallery/thumbs/06.jpg",
  "images/gallery/thumbs/07.jpg": "images/gallery/thumbs/07.jpg",
  "images/gallery/thumbs/08.jpg": "images/gallery/thumbs/08.jpg",
  "images/gallery/thumbs/09.jpg": "images/gallery/thumbs/09.jpg",
  "images/gallery/thumbs/10.jpg": "images/gallery/thumbs/10.jpg",
  "images/logo.jpg": "images/logo.jpg",
  "images/pic01.jpg": "images/pic01.jpg",
  "images/pic02.jpg": "images/pic02.jpg",
  "images/pic03.jpg": "images/pic03.jpg",
  "js/breakpoints.min.js": "js/breakpoints.min.js",
  "js/browser.min.js": "js/browser.min.js",
  "js/jquery.min.js": "js/jquery.min.js",
  "js/jquery.scrolly.min.js": "js/jquery.scrolly.min.js"
}